README.md
setup.py
smile/__init__.py
smile/app.py
smile/flags.py
smile.egg-info/PKG-INFO
smile.egg-info/SOURCES.txt
smile.egg-info/dependency_links.txt
smile.egg-info/not-zip-safe
smile.egg-info/requires.txt
smile.egg-info/top_level.txt