Metadata-Version: 1.0
Name: smile
Version: 0.1.0
Summary: smile-python is a modern absl-like python library for SMILE lab.
Home-page: https://github.com/uta-smile/smile-python/
Author: Zheng Xu
Author-email: zheng.xu@mavs.uta.edu
License: UNKNOWN
Platform: UNKNOWN
